proflex/init.py
proflex/proflex.py
proflex-0.1.0.dist-info/METADATA
proflex-0.1.0.dist-info/WHEEL
proflex-0.1.0.dist-info/entry_points.txt
proflex-0.1.0.dist-info/top_level.txt
proflex-0.1.0.dist-info/RECORD
